sleepwell/__init__.py
sleepwell/event.py
sleepwell/state.py
sleepwell/utils.py
sleepwell-0.1.3.dist-info/LICENSE
sleepwell-0.1.3.dist-info/WHEEL
sleepwell-0.1.3.dist-info/METADATA
sleepwell-0.1.3.dist-info/RECORD
