Metadata-Version: 2.1
Name: sleepwell
Version: 0.1.3
Summary: This package collect events and send them to sleepwell REST API
Author: Yves Tumushimire
Author-email: ytumushimire@truststamp.net
Requires-Python: >=3.7,<4.0
Classifier: Programming Language :: Python :: 3
Classifier: Programming Language :: Python :: 3.7
Classifier: Programming Language :: Python :: 3.8
Classifier: Programming Language :: Python :: 3.9
Requires-Dist: requests (>=2.26.0,<3.0.0)
